zc/recipe/testrunner/README.rst
zc/recipe/testrunner/__init__.py
zc/recipe/testrunner/tests.py
zc_recipe_testrunner-4.0.dist-info/licenses/LICENSE.txt
zc_recipe_testrunner-4.0.dist-info/METADATA
zc_recipe_testrunner-4.0.dist-info/WHEEL
zc_recipe_testrunner-4.0.dist-info/entry_points.txt
zc_recipe_testrunner-4.0.dist-info/top_level.txt
zc_recipe_testrunner-4.0.dist-info/RECORD
