Metadata-Version: 2.4
Name: zc.recipe.testrunner
Version: 4.0
Summary: ZC Buildout recipe for creating test runners
Home-page: https://github.com/zopefoundation/zc.recipe.testrunner
Author: Jim Fulton
Author-email: jim@zope.com
License: ZPL-2.1
Keywords: development build testing
Classifier: Development Status :: 5 - Production/Stable
Classifier: Framework :: Buildout
Classifier: Intended Audience :: Developers
Classifier: License :: OSI Approved :: Zope Public License
Classifier: Programming Language :: Python
Classifier: Programming Language :: Python :: 3
Classifier: Programming Language :: Python :: 3.9
Classifier: Programming Language :: Python :: 3.10
Classifier: Programming Language :: Python :: 3.11
Classifier: Programming Language :: Python :: 3.12
Classifier: Programming Language :: Python :: 3.13
Classifier: Programming Language :: Python :: Implementation :: CPython
Classifier: Programming Language :: Python :: Implementation :: PyPy
Classifier: Topic :: Software Development :: Build Tools
Classifier: Topic :: Software Development :: Libraries :: Python Modules
Requires-Python: >=3.9
License-File: LICENSE.txt
Requires-Dist: packaging>=23.2
Requires-Dist: zc.buildout>=1.2.0
Requires-Dist: zope.testrunner>=6.4
Requires-Dist: setuptools
Requires-Dist: zc.recipe.egg>=1.2.0
Provides-Extra: test
Requires-Dist: zope.testing; extra == "test"
Dynamic: author
Dynamic: author-email
Dynamic: classifier
Dynamic: description
Dynamic: home-page
Dynamic: keywords
Dynamic: license
Dynamic: license-file
Dynamic: provides-extra
Dynamic: requires-dist
Dynamic: requires-python
Dynamic: summary
